ripdb/__init__.py
ripdb-0.1.3.2.dist-info/AUTHORS.rst
ripdb-0.1.3.2.dist-info/LICENSE.rst
ripdb-0.1.3.2.dist-info/METADATA
ripdb-0.1.3.2.dist-info/WHEEL
ripdb-0.1.3.2.dist-info/top_level.txt
ripdb-0.1.3.2.dist-info/RECORD
