Metadata-Version: 2.1
Name: ripdb
Version: 0.1.3.2
Summary: Remotely accessible IPython-enabled debugger
Home-page: https://github.com/lebedov/ripdb/
Author: Lev E. Givon
Author-email: lev@columbia.edu
License: BSD
Platform: UNKNOWN
Classifier: Development Status :: 3 - Alpha
Classifier: Environment :: Console
Classifier: Framework :: IPython
Classifier: Intended Audience :: Developers
Classifier: License :: OSI Approved :: BSD License
Classifier: Operating System :: OS Independent
Classifier: Programming Language :: Python
Classifier: Topic :: Software Development
Requires-Dist: ipython (>=3.0)
Requires-Dist: six
